prototype_learning/__init__.py
prototype_learning/prototype_learning.py
prototype_learning/utils.py
prototype_learning-0.1.1.dist-info/LICENSE
prototype_learning-0.1.1.dist-info/WHEEL
prototype_learning-0.1.1.dist-info/METADATA
prototype_learning-0.1.1.dist-info/RECORD
