Metadata-Version: 2.1
Name: prototype-learning
Version: 0.1.1
Summary: A package for learning interpretable prototypes for prediction tasks.
License: MIT
Author: Anton Matsson
Requires-Python: >=3.9,<4.0
Classifier: License :: OSI Approved :: MIT License
Classifier: Programming Language :: Python :: 3
Classifier: Programming Language :: Python :: 3.10
Classifier: Programming Language :: Python :: 3.9
Requires-Dist: conda-lock (>=1.0.5,<2.0.0)
Requires-Dist: numpy (==1.20.3)
Requires-Dist: scikit-learn (>=1.1.1,<2.0.0)
Requires-Dist: skorch (>=0.11.0,<0.12.0)
Requires-Dist: torch (==1.11.0)
